sphinx_code_tabs/__init__.py
sphinx_code_tabs/code-tabs.css
sphinx_code_tabs/code-tabs.js
helveg_sphinx_code_tabs-0.2.0.dist-info/METADATA
helveg_sphinx_code_tabs-0.2.0.dist-info/UNLICENSE
helveg_sphinx_code_tabs-0.2.0.dist-info/WHEEL
helveg_sphinx_code_tabs-0.2.0.dist-info/top_level.txt
helveg_sphinx_code_tabs-0.2.0.dist-info/RECORD
