Metadata-Version: 2.1
Name: helveg-sphinx-code-tabs
Version: 0.2.0
Summary: Sphinx extension for adding alternative code-blocks as selectable tabs
Home-page: https://github.com/coldfix/sphinx-code-tabs
Download-URL: https://pypi.org/project/sphinx_code_tabs
Author: Thomas Gläßle
Author-email: thomas@coldfix.de
License: Unlicense
Keywords: sphinx extension alternative code-block tab notebook
Platform: any
Classifier: Development Status :: 4 - Beta
Classifier: Environment :: Plugins
Classifier: Intended Audience :: Developers
Classifier: License :: OSI Approved :: The Unlicense (Unlicense)
Classifier: Operating System :: OS Independent
Classifier: Programming Language :: Python :: 3
Classifier: Topic :: Documentation :: Sphinx
Requires-Python: >=3.5
License-File: UNLICENSE
Requires-Dist: sphinx (>=3)
Requires-Dist: importlib-resources ; python_version < "3.7"
Provides-Extra: doc
Requires-Dist: sphinx-rtd-theme ; extra == 'doc'
